dmdlab/__init__.py
dmdlab/__version__.py
dmdlab/dmd.py
dmdlab/plot.py
dmdlab/process.py
dmdlab-0.1.1.dist-info/WHEEL
dmdlab-0.1.1.dist-info/METADATA
dmdlab-0.1.1.dist-info/RECORD
