Metadata-Version: 2.1
Name: dmdlab
Version: 0.1.1
Summary: Dynamic mode decompositon in python.
License: MIT
Author: Andy Goldschmidt
Author-email: andygold@uw.edu
Requires-Python: >=3.7,<4.0
Classifier: License :: OSI Approved :: MIT License
Classifier: Programming Language :: Python :: 3
Classifier: Programming Language :: Python :: 3.7
Classifier: Programming Language :: Python :: 3.8
Provides-Extra: docs
Provides-Extra: test
Requires-Dist: ipykernel (>=5.2.1,<6.0.0)
Requires-Dist: jupyter_client (>=6.1.3,<7.0.0)
Requires-Dist: matplotlib (>=3.2.1,<4.0.0)
Requires-Dist: nbsphinx (>=0.6.1,<0.7.0); extra == "docs"
Requires-Dist: numpy (>=1.18.3,<2.0.0)
Requires-Dist: pytest (>=5.2,<6.0); extra == "test"
Requires-Dist: scipy (>=1.4.1,<2.0.0)
Requires-Dist: sphinx (>=3.0.2,<4.0.0); extra == "docs"
